adafruit_circuitpython_emc2101-1.2.12.dist-info/licenses/LICENSE
adafruit_emc2101/__init__.py
adafruit_emc2101/emc2101_enums.py
adafruit_emc2101/emc2101_ext.py
adafruit_emc2101/emc2101_fanspeed.py
adafruit_emc2101/emc2101_lut.py
adafruit_emc2101/emc2101_regs.py
adafruit_circuitpython_emc2101-1.2.12.dist-info/METADATA
adafruit_circuitpython_emc2101-1.2.12.dist-info/WHEEL
adafruit_circuitpython_emc2101-1.2.12.dist-info/top_level.txt
adafruit_circuitpython_emc2101-1.2.12.dist-info/RECORD
