Metadata-Version: 2.4
Name: adafruit-circuitpython-emc2101
Version: 1.2.12
Summary: Brushless fan controller
Author-email: Adafruit Industries <circuitpython@adafruit.com>
License: MIT
Project-URL: Homepage, https://github.com/adafruit/Adafruit_CircuitPython_EMC2101
Keywords: adafruit,blinka,circuitpython,micropython,emc2101,Fan,Controller,RPM,Noctua,Sunon,Cooling,Thermostat,PWM,Tach
Classifier: Intended Audience :: Developers
Classifier: Topic :: Software Development :: Libraries
Classifier: Topic :: Software Development :: Embedded Systems
Classifier: Topic :: System :: Hardware
Classifier: License :: OSI Approved :: MIT License
Classifier: Programming Language :: Python :: 3
License-File: LICENSE
Requires-Dist: Adafruit-Blinka
Requires-Dist: adafruit-circuitpython-register
Requires-Dist: adafruit-circuitpython-busdevice
Provides-Extra: optional
Dynamic: license-file
